awsx.py
awsx_cli-1.2.0.dist-info/LICENSE
awsx_cli-1.2.0.dist-info/METADATA
awsx_cli-1.2.0.dist-info/WHEEL
awsx_cli-1.2.0.dist-info/entry_points.txt
awsx_cli-1.2.0.dist-info/top_level.txt
awsx_cli-1.2.0.dist-info/RECORD
