Metadata-Version: 2.1
Name: awsx-cli
Version: 1.2.0
Summary: AWS credential management tool
Home-page: https://github.com/mertongngl/awsx
Author: Mert Öngengil, Mehmet Eraslan, Engin Can Höke
Classifier: License :: OSI Approved :: MIT License
Classifier: Programming Language :: Python :: 3
License-File: LICENSE
Requires-Dist: argparse
